dctag/__init__.py
dctag/__main__.py
dctag/_version.py
dctag/scores.py
dctag/session.py
dctag/gui/__init__.py
dctag/gui/main.py
dctag/gui/main.ui
dctag/gui/simple_plot_widget.py
dctag/gui/tab_binary.py
dctag/gui/tab_binary.ui
dctag/gui/tab_multiple.py
dctag/gui/tab_multiple.ui
dctag/gui/tab_session.py
dctag/gui/tab_session.ui
dctag/gui/widget_img.py
dctag/gui/widget_scat.py
dctag/gui/widget_vis.py
dctag/gui/widget_vis.ui
dctag/img/__init__.py
dctag/img/icon.png
dctag/resources/__init__.py
dctag/resources/tag_ml_scores_blood.json
dctag/resources/tag_userdef.json
dctag-0.8.1.dist-info/licenses/LICENSE
dctag-0.8.1.dist-info/METADATA
dctag-0.8.1.dist-info/WHEEL
dctag-0.8.1.dist-info/entry_points.txt
dctag-0.8.1.dist-info/top_level.txt
dctag-0.8.1.dist-info/RECORD
